CMakeLists.txt
LICENSE
MANIFEST.in
README.md
pybind11.cmake
pyproject.toml
setup.py
ctreelearn/CMakeLists.txt
ctreelearn/ctreelearn.cpp
ctreelearn.egg-info/PKG-INFO
ctreelearn.egg-info/SOURCES.txt
ctreelearn.egg-info/dependency_links.txt
ctreelearn.egg-info/not-zip-safe
ctreelearn.egg-info/top_level.txt
ctreelearn/include/AdjacencyRelation.hpp
ctreelearn/include/AdjacencyUC.hpp
ctreelearn/include/AttributeComputedIncrementally.hpp
ctreelearn/include/AttributeFilters.hpp
ctreelearn/include/BuilderComponentTreeByUnionFind.hpp
ctreelearn/include/BuilderTreeOfShapeByUnionFind.hpp
ctreelearn/include/Common.hpp
ctreelearn/include/ComputerDerivatives.hpp
ctreelearn/include/ComputerMSER.hpp
ctreelearn/include/ImageUtils.hpp
ctreelearn/include/MorphologicalTree.hpp
ctreelearn/include/NodeMT.hpp
ctreelearn/pybind/AttributeComputedIncrementallyPybind.hpp
ctreelearn/pybind/AttributeFiltersPybind.hpp
ctreelearn/pybind/ComputerDerivativesPybind.hpp
ctreelearn/pybind/MorphologicalTreePybind.hpp
ctreelearn/pybind/PybindUtils.hpp
ctreelearn/src/AdjacencyRelation.cpp
ctreelearn/src/AttributeComputedIncrementally.cpp
ctreelearn/src/AttributeFilters.cpp
ctreelearn/src/BuilderComponentTreeByUnionFind.cpp
ctreelearn/src/BuilderTreeOfShapeByUnionFind.cpp
ctreelearn/src/ComputerMSER.cpp
ctreelearn/src/MorphologicalTree.cpp
ctreelearn/src/NodeMT.cpp
ctreelearn/test/Tests.hpp
ctreelearn/test/testeComputerAttribute.cpp
ctreelearn/test/testeComputerAttributePybind.cpp
ctreelearn/test/testeTensor.cpp
ctreelearn/test/testeTreeOfShapes.cpp
python/__init__.py
python/dataset.py
python/featureSelection.py
python/models.py
python/test.py
python/version.py