Metadata-Version: 2.1
Name: ctreelearn
Version: 0.2.3
Summary: A simple library for learning of connected filters based on component trees
Home-page: https://github.com/wonderalexandre/ComponentTreeLearn
Author: Wonder Alexandre Luz Alves
Author-email: worderalexandre@gmail.com
License: GPL-3.0
Keywords: machine learning,morphological trees,mathematical morphology
Classifier: Development Status :: 3 - Alpha
Classifier: Intended Audience :: Science/Research
Classifier: Topic :: Scientific/Engineering :: Image Processing
Classifier: Programming Language :: Python
Classifier: Programming Language :: C++
License-File: LICENSE
